{
	"info": {
		"_postman_id": "cc1fc7fa-3a5e-4813-a403-00172c396327",
		"name": "Vouchers",
		"schema": "https://schema.getpostman.com/json/collection/v2.1.0/collection.json",
		"_exporter_id": "6057984"
	},
	"item": [
		{
			"name": "Add User",
			"request": {
				"method": "GET",
				"header": []
			},
			"response": []
		},
		{
			"name": "Login as Creator",
			"request": {
				"method": "GET",
				"header": []
			},
			"response": []
		},
		{
			"name": "Add Voucher",
			"request": {
				"method": "GET",
				"header": []
			},
			"response": []
		},
		{
			"name": "edit voucher",
			"request": {
				"method": "GET",
				"header": []
			},
			"response": []
		},
		{
			"name": "Delete Voucher",
			"request": {
				"method": "GET",
				"header": []
			},
			"response": []
		},
		{
			"name": "Get Voucher List",
			"request": {
				"method": "GET",
				"header": []
			},
			"response": []
		},
		{
			"name": "Add Order",
			"request": {
				"method": "GET",
				"header": []
			},
			"response": []
		},
		{
			"name": "List Order",
			"request": {
				"method": "GET",
				"header": []
			},
			"response": []
		}
	]
}